lora_adapters/__init__.py
lora_adapters/layers.py
lora_adapters/utils.py
lora_adapters-0.1.4.dist-info/LICENSE.md
lora_adapters-0.1.4.dist-info/METADATA
lora_adapters-0.1.4.dist-info/WHEEL
lora_adapters-0.1.4.dist-info/top_level.txt
lora_adapters-0.1.4.dist-info/RECORD
