Metadata-Version: 2.1
Name: lora_adapters
Version: 0.1.4
Summary: PyTorch implementation of low-rank adaptation (LoRA), a parameter-efficient approach to adapt a large pre-trained deep learning model which obtains performance on-par with full fine-tuning.
Home-page: https://github.com/kiansierra/lora-adapters
Author: Kian Sierra McGettigan
Author-email: kiansierra90@gmail.com
Classifier: Programming Language :: Python :: 3
Classifier: License :: OSI Approved :: MIT License
Classifier: Operating System :: OS Independent
Requires-Python: >=3.7
License-File: LICENSE.md
